{
  "schema_version": 1,
  "as_of": "2026-05-03",
  "notes": "Curated MCP server directory. Tier classification: free (zero cost, self-host or hosted free tier), freemium (free tier with paid upgrades), paid (paid-only or usage-billed). The 'partnership_potential' flag marks vendors with revenue-share or referral programs we may pursue.",
  "categories": [
    "filesystem",
    "code",
    "data",
    "search",
    "automation",
    "communication",
    "productivity",
    "browser",
    "design",
    "observability",
    "payments",
    "ai",
    "knowledge",
    "crm",
    "demo"
  ],
  "servers": [
    {
      "id": "filesystem",
      "name": "Filesystem",
      "vendor": "MCP Project",
      "url": "https://github.com/modelcontextprotocol/servers/tree/main/src/filesystem",
      "category": "filesystem",
      "tier": "free",
      "self_hostable": true,
      "partnership_potential": false,
      "description": "Sandboxed read/write access to files and directories."
    },
    {
      "id": "git",
      "name": "Git",
      "vendor": "MCP Project",
      "url": "https://github.com/modelcontextprotocol/servers/tree/main/src/git",
      "category": "code",
      "tier": "free",
      "self_hostable": true,
      "partnership_potential": false,
      "description": "Read git history, diffs, and branches."
    },
    {
      "id": "github",
      "name": "GitHub",
      "vendor": "GitHub",
      "url": "https://github.com/github/github-mcp-server",
      "category": "code",
      "tier": "freemium",
      "self_hostable": false,
      "partnership_potential": false,
      "description": "Issues, PRs, code search. 5k req/hr free."
    },
    {
      "id": "gitlab",
      "name": "GitLab",
      "vendor": "GitLab",
      "url": "https://github.com/modelcontextprotocol/servers/tree/main/src/gitlab",
      "category": "code",
      "tier": "freemium",
      "self_hostable": true,
      "partnership_potential": false,
      "description": "Repos, MRs, pipelines on gitlab.com or self-hosted."
    },
    {
      "id": "postgres",
      "name": "Postgres",
      "vendor": "MCP Project",
      "url": "https://github.com/modelcontextprotocol/servers/tree/main/src/postgres",
      "category": "data",
      "tier": "free",
      "self_hostable": true,
      "partnership_potential": false,
      "description": "Read-only SQL queries against a Postgres DB."
    },
    {
      "id": "sqlite",
      "name": "SQLite",
      "vendor": "MCP Project",
      "url": "https://github.com/modelcontextprotocol/servers/tree/main/src/sqlite",
      "category": "data",
      "tier": "free",
      "self_hostable": true,
      "partnership_potential": false,
      "description": "Local SQLite database access."
    },
    {
      "id": "memory",
      "name": "Memory",
      "vendor": "MCP Project",
      "url": "https://github.com/modelcontextprotocol/servers/tree/main/src/memory",
      "category": "knowledge",
      "tier": "free",
      "self_hostable": true,
      "partnership_potential": false,
      "description": "In-process knowledge graph for cross-turn memory."
    },
    {
      "id": "fetch",
      "name": "Fetch",
      "vendor": "MCP Project",
      "url": "https://github.com/modelcontextprotocol/servers/tree/main/src/fetch",
      "category": "browser",
      "tier": "free",
      "self_hostable": true,
      "partnership_potential": false,
      "description": "Convert HTTP URLs to markdown; html_to_markdown utility."
    },
    {
      "id": "puppeteer",
      "name": "Puppeteer",
      "vendor": "community",
      "url": "https://github.com/modelcontextprotocol/servers/tree/main/src/puppeteer",
      "category": "browser",
      "tier": "free",
      "self_hostable": true,
      "partnership_potential": false,
      "description": "Headless Chrome \u2014 navigate, click, screenshot."
    },
    {
      "id": "brave_search",
      "name": "Brave Search",
      "vendor": "Brave",
      "url": "https://github.com/modelcontextprotocol/servers/tree/main/src/brave-search",
      "category": "search",
      "tier": "freemium",
      "self_hostable": false,
      "partnership_potential": true,
      "pricing": "Free 2k req/mo; paid from $5/mo",
      "description": "Privacy-respecting web + local search."
    },
    {
      "id": "tavily",
      "name": "Tavily",
      "vendor": "Tavily",
      "url": "https://docs.tavily.com/docs/integrations/mcp",
      "category": "search",
      "tier": "freemium",
      "self_hostable": false,
      "partnership_potential": true,
      "pricing": "Free 1k credits/mo; paid plans from $30/mo",
      "description": "Search API tuned for agentic workflows."
    },
    {
      "id": "exa",
      "name": "Exa",
      "vendor": "Exa Labs",
      "url": "https://github.com/exa-labs/exa-mcp-server",
      "category": "search",
      "tier": "freemium",
      "self_hostable": false,
      "partnership_potential": true,
      "pricing": "Free 1k searches/mo; paid usage-based",
      "description": "Neural search engine with semantic ranking."
    },
    {
      "id": "perplexity",
      "name": "Perplexity",
      "vendor": "Perplexity",
      "url": "https://docs.perplexity.ai/guides/mcp-server",
      "category": "search",
      "tier": "paid",
      "self_hostable": false,
      "partnership_potential": true,
      "pricing": "Pay-per-token via API",
      "description": "Online search with citations."
    },
    {
      "id": "firecrawl",
      "name": "Firecrawl",
      "vendor": "Firecrawl",
      "url": "https://github.com/mendableai/firecrawl-mcp-server",
      "category": "browser",
      "tier": "freemium",
      "self_hostable": false,
      "partnership_potential": true,
      "pricing": "Free trial; plans from $16/mo",
      "description": "Crawl + scrape with JS rendering."
    },
    {
      "id": "browserbase",
      "name": "Browserbase",
      "vendor": "Browserbase",
      "url": "https://docs.browserbase.com/integrations/mcp",
      "category": "browser",
      "tier": "paid",
      "self_hostable": false,
      "partnership_potential": true,
      "pricing": "Usage-billed; trial available",
      "description": "Hosted headless browsers with stealth + sessions."
    },
    {
      "id": "slack",
      "name": "Slack",
      "vendor": "Slack",
      "url": "https://github.com/modelcontextprotocol/servers/tree/main/src/slack",
      "category": "communication",
      "tier": "freemium",
      "self_hostable": true,
      "partnership_potential": false,
      "description": "Send messages, read channels, manage threads."
    },
    {
      "id": "linear",
      "name": "Linear",
      "vendor": "Linear",
      "url": "https://linear.app/changelog/2026-mcp",
      "category": "productivity",
      "tier": "freemium",
      "self_hostable": false,
      "partnership_potential": true,
      "pricing": "Free for small teams; paid per-seat",
      "description": "Issues, projects, sprints."
    },
    {
      "id": "notion",
      "name": "Notion",
      "vendor": "Notion",
      "url": "https://www.notion.so/mcp",
      "category": "productivity",
      "tier": "freemium",
      "self_hostable": false,
      "partnership_potential": true,
      "pricing": "Free personal; paid teams",
      "description": "Pages, databases, blocks."
    },
    {
      "id": "atlassian_jira",
      "name": "Jira",
      "vendor": "Atlassian",
      "url": "https://www.atlassian.com/blog/announcements/mcp-server",
      "category": "productivity",
      "tier": "freemium",
      "self_hostable": false,
      "partnership_potential": true,
      "pricing": "Free up to 10 users; paid per-seat",
      "description": "Issues, sprints, projects."
    },
    {
      "id": "atlassian_conf",
      "name": "Confluence",
      "vendor": "Atlassian",
      "url": "https://www.atlassian.com/blog/announcements/mcp-server",
      "category": "knowledge",
      "tier": "freemium",
      "self_hostable": false,
      "partnership_potential": true,
      "pricing": "Free up to 10 users; paid per-seat",
      "description": "Pages, spaces, search."
    },
    {
      "id": "asana",
      "name": "Asana",
      "vendor": "Asana",
      "url": "https://developers.asana.com/docs/mcp",
      "category": "productivity",
      "tier": "freemium",
      "self_hostable": false,
      "partnership_potential": true,
      "pricing": "Free up to 15 users; paid per-seat",
      "description": "Tasks, projects, portfolios."
    },
    {
      "id": "figma",
      "name": "Figma Dev Mode",
      "vendor": "Figma",
      "url": "https://help.figma.com/hc/en-us/articles/32132100833559",
      "category": "design",
      "tier": "free",
      "self_hostable": false,
      "partnership_potential": false,
      "description": "Read live design file structure and tokens."
    },
    {
      "id": "sentry",
      "name": "Sentry",
      "vendor": "Sentry",
      "url": "https://docs.sentry.io/product/integrations/mcp",
      "category": "observability",
      "tier": "freemium",
      "self_hostable": true,
      "partnership_potential": true,
      "pricing": "Free 5k events/mo; paid from $26/mo",
      "description": "Error reports, performance, releases."
    },
    {
      "id": "cloudflare",
      "name": "Cloudflare",
      "vendor": "Cloudflare",
      "url": "https://developers.cloudflare.com/mcp",
      "category": "data",
      "tier": "freemium",
      "self_hostable": false,
      "partnership_potential": true,
      "pricing": "Free tier; usage-billed",
      "description": "Workers, KV, R2, D1, analytics."
    },
    {
      "id": "stripe",
      "name": "Stripe",
      "vendor": "Stripe",
      "url": "https://stripe.com/blog/mcp-server",
      "category": "payments",
      "tier": "paid",
      "self_hostable": false,
      "partnership_potential": true,
      "pricing": "Standard transaction fees apply",
      "description": "Payments, subscriptions, customers."
    },
    {
      "id": "zapier",
      "name": "Zapier",
      "vendor": "Zapier",
      "url": "https://zapier.com/mcp",
      "category": "automation",
      "tier": "freemium",
      "self_hostable": false,
      "partnership_potential": true,
      "pricing": "Free 100 tasks/mo; paid from $20/mo",
      "description": "Bridge to thousands of SaaS tools via Zaps."
    },
    {
      "id": "vectara",
      "name": "Vectara",
      "vendor": "Vectara",
      "url": "https://docs.vectara.com/docs/mcp",
      "category": "ai",
      "tier": "freemium",
      "self_hostable": false,
      "partnership_potential": true,
      "pricing": "Free 50 MB; paid usage",
      "description": "Semantic search + RAG over your corpus."
    },
    {
      "id": "e2b",
      "name": "E2B Sandbox",
      "vendor": "E2B",
      "url": "https://e2b.dev/docs/mcp",
      "category": "code",
      "tier": "paid",
      "self_hostable": false,
      "partnership_potential": true,
      "pricing": "Pay-per-second sandbox time",
      "description": "Hosted code execution sandbox."
    },
    {
      "id": "apollo",
      "name": "Apollo.io",
      "vendor": "Apollo",
      "url": "https://docs.apollo.io/mcp",
      "category": "crm",
      "tier": "paid",
      "self_hostable": false,
      "partnership_potential": true,
      "pricing": "Paid plans from $49/mo",
      "description": "Contacts, companies, sequences."
    },
    {
      "id": "everything",
      "name": "Everything",
      "vendor": "MCP Project",
      "url": "https://github.com/modelcontextprotocol/servers/tree/main/src/everything",
      "category": "demo",
      "tier": "free",
      "self_hostable": true,
      "partnership_potential": false,
      "description": "Reference server exercising every MCP feature."
    },
    {
      "id": "time",
      "name": "Time",
      "vendor": "MCP Project",
      "url": "https://github.com/modelcontextprotocol/servers/tree/main/src/time",
      "category": "productivity",
      "tier": "free",
      "self_hostable": true,
      "partnership_potential": false,
      "description": "Timezone conversions and current time."
    },
    {
      "id": "sequential_thinking",
      "name": "Sequential Thinking",
      "vendor": "MCP Project",
      "url": "https://github.com/modelcontextprotocol/servers/tree/main/src/sequentialthinking",
      "category": "ai",
      "tier": "free",
      "self_hostable": true,
      "partnership_potential": false,
      "description": "Structured chain-of-thought scratchpad."
    }
  ]
}
